[
  {
    "py/object": "model.contact.Contact",
    "firstname": "firstnamekI",
    "lastname": "lastname<0TV{7pstD\"Hr=A3&|j",
    "nickname": "nicknameAy+yv}G55FbKTb2759",
    "photo": null,
    "title": "titleS{$>S>4;uOg1W/UWEZm",
    "company": "companyOKWcXXBk",
    "address": "address 1xfl[W@ZB)pE[Cz",
    "home_number": "home_number183261379761557",
    "mobile_number": "mobile_number2",
    "work_number": "work_number8",
    "fax_number": "fax_number3394133451",
    "email": "emailw.#.Q~",
    "email2": "email2t!1cy*B&V",
    "email3": null,
    "home_page": "home_page}n2k}1VogbI",
    "birthday": null,
    "birthmonth": null,
    "birthyear": null,
    "annday": null,
    "annmonth": null,
    "annyear": null,
    "address2": null,
    "phone2": null,
    "notes": null,
    "id": null,
    "all_phones_from_home_page": null,
    "all_emails_from_home_page": null
  },
  {
    "py/object": "model.contact.Contact",
    "firstname": "firstname-K-Gx",
    "lastname": "lastname:^",
    "nickname": "nicknameN8e]IK",
    "photo": null,
    "title": "title",
    "company": "company?>{i|IR40j@DP",
    "address": "address]u<[",
    "home_number": "home_number44493904",
    "mobile_number": "mobile_number7978120850883020070",
    "work_number": "work_number967667854162",
    "fax_number": "fax_number027",
    "email": "emailTl3A",
    "email2": "email2}^Pw'Oc9<~i",
    "email3": null,
    "home_page": "home_page[",
    "birthday": null,
    "birthmonth": null,
    "birthyear": null,
    "annday": null,
    "annmonth": null,
    "annyear": null,
    "address2": null,
    "phone2": null,
    "notes": null,
    "id": null,
    "all_phones_from_home_page": null,
    "all_emails_from_home_page": null
  },
  {
    "py/object": "model.contact.Contact",
    "firstname": "firstname$q\\+Wf5w",
    "lastname": "lastname+{*m",
    "nickname": "nicknamef6qofR]i%JQZkA$]",
    "photo": null,
    "title": "title3&FBm/G:ZLN0>MXc2b",
    "company": "company=)7[UC^@:ke8sx<BC6",
    "address": "addresso#",
    "home_number": "home_number68363",
    "mobile_number": "mobile_number965040320749376",
    "work_number": "work_number702852511875273",
    "fax_number": "fax_number035593582749837",
    "email": "emailL2>#_ suT-tvO",
    "email2": "email2y`1GBw{O%=8^'|k}G31",
    "email3": null,
    "home_page": "home_pageM&_",
    "birthday": null,
    "birthmonth": null,
    "birthyear": null,
    "annday": null,
    "annmonth": null,
    "annyear": null,
    "address2": null,
    "phone2": null,
    "notes": null,
    "id": null,
    "all_phones_from_home_page": null,
    "all_emails_from_home_page": null
  },
  {
    "py/object": "model.contact.Contact",
    "firstname": "firstname6OoJ",
    "lastname": "lastnameUpU{)zC)vss*v-5D",
    "nickname": "nicknameIK3S{czu3NL!",
    "photo": null,
    "title": "titleM6nbxSfn8",
    "company": "companya)KHo<A0KsD\\L",
    "address": "addressJ1WIk4ko$`0iS*",
    "home_number": "home_number2560",
    "mobile_number": "mobile_number71597932",
    "work_number": "work_number097015629739832",
    "fax_number": "fax_number8044",
    "email": "emailc5",
    "email2": "email2S*]%0#l:r/~J{o:eE",
    "email3": null,
    "home_page": "home_page/T",
    "birthday": null,
    "birthmonth": null,
    "birthyear": null,
    "annday": null,
    "annmonth": null,
    "annyear": null,
    "address2": null,
    "phone2": null,
    "notes": null,
    "id": null,
    "all_phones_from_home_page": null,
    "all_emails_from_home_page": null
  },
  {
    "py/object": "model.contact.Contact",
    "firstname": "firstnameHDP,*;[",
    "lastname": "lastname5b?,/H",
    "nickname": "nickname,eiK>L",
    "photo": null,
    "title": "titlefm/.2)",
    "company": "company",
    "address": "address+?MC&",
    "home_number": "home_number6461522055096687",
    "mobile_number": "mobile_number7257517497",
    "work_number": "work_number1",
    "fax_number": "fax_number130",
    "email": "email=",
    "email2": "email20,0T`%(/h%",
    "email3": null,
    "home_page": "home_pageqXs<GA)P4wO*",
    "birthday": null,
    "birthmonth": null,
    "birthyear": null,
    "annday": null,
    "annmonth": null,
    "annyear": null,
    "address2": null,
    "phone2": null,
    "notes": null,
    "id": null,
    "all_phones_from_home_page": null,
    "all_emails_from_home_page": null
  }
]